biem_helmholtz_sphere/__init__.py
biem_helmholtz_sphere/__main__.py
biem_helmholtz_sphere/cli.py
biem_helmholtz_sphere/main.py
biem_helmholtz_sphere/py.typed
biem_helmholtz_sphere-0.0.0.dist-info/licenses/LICENSE
biem_helmholtz_sphere-0.0.0.dist-info/METADATA
biem_helmholtz_sphere-0.0.0.dist-info/WHEEL
biem_helmholtz_sphere-0.0.0.dist-info/entry_points.txt
biem_helmholtz_sphere-0.0.0.dist-info/top_level.txt
biem_helmholtz_sphere-0.0.0.dist-info/RECORD
